<?xml version="1.0" encoding="utf-8" ?>
<dwsync>
<file name="Capture.PNG" server="ftp.luisintiascaledmodels.com/public_html/" local="130631734207678839" remote="130630969800000000" Dst="0" />
<file name="IMG_5980.JPG" server="ftp.luisintiascaledmodels.com/public_html/" local="130631734566799380" remote="130630972800000000" Dst="0" />
<file name="IMG_6011.JPG" server="ftp.luisintiascaledmodels.com/public_html/" local="130631734628722922" remote="130630972800000000" Dst="0" />
<file name="IMG_5984.JPG" server="ftp.luisintiascaledmodels.com/public_html/" local="130631734668985224" remote="130630973400000000" Dst="0" />
<file name="IMG_6016.JPG" server="ftp.luisintiascaledmodels.com/public_html/" local="130631734902758596" remote="130630973400000000" Dst="0" />
<file name="IMG_6017.JPG" server="ftp.luisintiascaledmodels.com/public_html/" local="130631735051827122" remote="130630974600000000" Dst="0" />
<file name="IMG_6095.JPG" server="ftp.luisintiascaledmodels.com/public_html/" local="130631735391356542" remote="130630974000000000" Dst="0" />
<file name="IMG_6110.JPG" server="ftp.luisintiascaledmodels.com/public_html/" local="130631735393696676" remote="130630974600000000" Dst="0" />
<file name="IMG_6212.JPG" server="ftp.luisintiascaledmodels.com/public_html/" local="130631735634750463" remote="130630975200000000" Dst="0" />
<file name="IMG_6319.JPG" server="ftp.luisintiascaledmodels.com/public_html/" local="130631735959039011" remote="130630975200000000" Dst="0" />
<file name="IMG_6266.JPG" server="ftp.luisintiascaledmodels.com/public_html/" local="130631736058684711" remote="130630975200000000" Dst="0" />
<file name="IMG_6356.JPG" server="ftp.luisintiascaledmodels.com/public_html/" local="130631736268256698" remote="130630976400000000" Dst="0" />
<file name="IMG_6359.JPG" server="ftp.luisintiascaledmodels.com/public_html/" local="130631736710892015" remote="130630975800000000" Dst="0" />
<file name="IMG_6428.JPG" server="ftp.luisintiascaledmodels.com/public_html/" local="130631736722362671" remote="130630975800000000" Dst="0" />
<file name="IMG_6473.JPG" server="ftp.luisintiascaledmodels.com/public_html/" local="130631736907473259" remote="130630976400000000" Dst="0" />
<file name="IMG_6490.JPG" server="ftp.luisintiascaledmodels.com/public_html/" local="130631737117895294" remote="130630976400000000" Dst="0" />
<file name="IMG_6496.JPG" server="ftp.luisintiascaledmodels.com/public_html/" local="130631737342198124" remote="130630977000000000" Dst="0" />
<file name="IMG_6493.JPG" server="ftp.luisintiascaledmodels.com/public_html/" local="130631737356558945" remote="130630977000000000" Dst="0" />
<file name="IMG_6871.JPG" server="ftp.luisintiascaledmodels.com/public_html/" local="130631737848677092" remote="130630978200000000" Dst="0" />
<file name="IMG_6982.JPG" server="ftp.luisintiascaledmodels.com/public_html/" local="130631737956453257" remote="130630978200000000" Dst="0" />
<file name="IMG_7045.JPG" server="ftp.luisintiascaledmodels.com/public_html/" local="130631737979994603" remote="130630978200000000" Dst="0" />
<file name="IMG_7081.JPG" server="ftp.luisintiascaledmodels.com/public_html/" local="130631738463422254" remote="130630978800000000" Dst="0" />
<file name="IMG_7065.JPG" server="ftp.luisintiascaledmodels.com/public_html/" local="130631738471562719" remote="130630978800000000" Dst="0" />
<file name="IMG_7089.JPG" server="ftp.luisintiascaledmodels.com/public_html/" local="130631738502954515" remote="130630979400000000" Dst="0" />
<file name="IMG_7110.JPG" server="ftp.luisintiascaledmodels.com/public_html/" local="130631738880806127" remote="130630979400000000" Dst="0" />
<file name="IMG_7098.JPG" server="ftp.luisintiascaledmodels.com/public_html/" local="130631738894346901" remote="130630979400000000" Dst="0" />
<file name="IMG_7115.JPG" server="ftp.luisintiascaledmodels.com/public_html/" local="130631738927578802" remote="130630980600000000" Dst="0" />
<file name="IMG_7125.JPG" server="ftp.luisintiascaledmodels.com/public_html/" local="130631739323891470" remote="130630980600000000" Dst="0" />
<file name="IMG_7143.JPG" server="ftp.luisintiascaledmodels.com/public_html/" local="130631739341032450" remote="130630981200000000" Dst="0" />
<file name="IMG_7136.JPG" server="ftp.luisintiascaledmodels.com/public_html/" local="130631739391615343" remote="130630980600000000" Dst="0" />
<file name="IMG_7162.JPG" server="ftp.luisintiascaledmodels.com/public_html/" local="130631739691792513" remote="130630981800000000" Dst="0" />
<file name="IMG_7169.JPG" server="ftp.luisintiascaledmodels.com/public_html/" local="130631739722024242" remote="130630981200000000" Dst="0" />
<file name="IMG_7203.JPG" server="ftp.luisintiascaledmodels.com/public_html/" local="130631739880453303" remote="130630982400000000" Dst="0" />
<file name="IMG_7206.JPG" server="ftp.luisintiascaledmodels.com/public_html/" local="130631740132457717" remote="130630982400000000" Dst="0" />
<file name="IMG_7234.JPG" server="ftp.luisintiascaledmodels.com/public_html/" local="130631740147108555" remote="130630982400000000" Dst="0" />
<file name="IMG_7248.JPG" server="ftp.luisintiascaledmodels.com/public_html/" local="130631740253134620" remote="130630983000000000" Dst="0" />
<file name="IMG_7288.JPG" server="ftp.luisintiascaledmodels.com/public_html/" local="130631740573012916" remote="130630983000000000" Dst="0" />
<file name="IMG_7276.JPG" server="ftp.luisintiascaledmodels.com/public_html/" local="130631740582253444" remote="130630983600000000" Dst="0" />
<file name="IMG_7313.JPG" server="ftp.luisintiascaledmodels.com/public_html/" local="130631740624455858" remote="130630983600000000" Dst="0" />
<file name="IMG_7349.JPG" server="ftp.luisintiascaledmodels.com/public_html/" local="130631740838408095" remote="130630984200000000" Dst="0" />
<file name="IMG_7318.JPG" server="ftp.luisintiascaledmodels.com/public_html/" local="130631740983456392" remote="130630983600000000" Dst="0" />
<file name="IMG_7353.JPG" server="ftp.luisintiascaledmodels.com/public_html/" local="130631741224420174" remote="130630984800000000" Dst="0" />
<file name="IMG_7373.JPG" server="ftp.luisintiascaledmodels.com/public_html/" local="130631741231630586" remote="130630984800000000" Dst="0" />
<file name="IMG_8234.JPG" server="ftp.luisintiascaledmodels.com/public_html/" local="130631741519277039" remote="130630984800000000" Dst="0" />
<file name="IMG_8261.JPG" server="ftp.luisintiascaledmodels.com/public_html/" local="130631741629483342" remote="130630986000000000" Dst="0" />
<file name="IMG_8283.JPG" server="ftp.luisintiascaledmodels.com/public_html/" local="130631741644154181" remote="130630985400000000" Dst="0" />
<file name="IMG_8382.JPG" server="ftp.luisintiascaledmodels.com/public_html/" local="130631741927800405" remote="130630986000000000" Dst="0" />
<file name="IMG_8416.JPG" server="ftp.luisintiascaledmodels.com/public_html/" local="130631742100870304" remote="130630987200000000" Dst="0" />
<file name="IMG_8350.JPG" server="ftp.luisintiascaledmodels.com/public_html/" local="130631742119921394" remote="130630986000000000" Dst="0" />
<file name="IMG_8454.JPG" server="ftp.luisintiascaledmodels.com/public_html/" local="130631742360855174" remote="130630986600000000" Dst="0" />
<file name="IMG_8468.JPG" server="ftp.luisintiascaledmodels.com/public_html/" local="130631742477181828" remote="130630987800000000" Dst="0" />
<file name="IMG_8539.JPG" server="ftp.luisintiascaledmodels.com/public_html/" local="130631742661582375" remote="130630987200000000" Dst="0" />
<file name="IMG_8463.JPG" server="ftp.luisintiascaledmodels.com/public_html/" local="130631742687613864" remote="130630986600000000" Dst="0" />
<file name="IMG_8630.JPG" server="ftp.luisintiascaledmodels.com/public_html/" local="130631742910026585" remote="130630988400000000" Dst="0" />
<file name="IMG_8669.JPG" server="ftp.luisintiascaledmodels.com/public_html/" local="130631742976910411" remote="130630988400000000" Dst="0" />
<file name="IMG_8704.JPG" server="ftp.luisintiascaledmodels.com/public_html/" local="130631743166341245" remote="130630988400000000" Dst="0" />
<file name="IMG_8715.JPG" server="ftp.luisintiascaledmodels.com/public_html/" local="130631743343751393" remote="130630989000000000" Dst="0" />
<file name="IMG_8778.JPG" server="ftp.luisintiascaledmodels.com/public_html/" local="130631743427216167" remote="130630989000000000" Dst="0" />
<file name="IMG_8794.JPG" server="ftp.luisintiascaledmodels.com/public_html/" local="130631743727823360" remote="130630989000000000" Dst="0" />
<file name="New folder.JPG" server="ftp.luisintiascaledmodels.com/public_html/" local="130631743754984914" remote="130630308000000000" Dst="0" />
<file name="cmaa1.jpg" server="ftp.luisintiascaledmodels.com/public_html/" local="130631743761695298" remote="130627644000000000" Dst="0" />
<file name="cmaa6.jpg" server="ftp.luisintiascaledmodels.com/public_html/" local="130631743772325906" remote="130627644000000000" Dst="0" />
<file name="cmaa9.jpg" server="ftp.luisintiascaledmodels.com/public_html/" local="130631743788806848" remote="130627644000000000" Dst="0" />
<file name="hcob3.jpg" server="ftp.luisintiascaledmodels.com/public_html/" local="130631743805607809" remote="130627644000000000" Dst="0" />
<file name="hcob6.jpg" server="ftp.luisintiascaledmodels.com/public_html/" local="130631743815998404" remote="130627644000000000" Dst="0" />
<file name="hcob9.jpg" server="ftp.luisintiascaledmodels.com/public_html/" local="130631743826138984" remote="130627644000000000" Dst="0" />
<file name="ThisIMG.JPG" server="ftp.luisintiascaledmodels.com/public_html/" local="130631743838309680" remote="130630307400000000" Dst="0" />
<file name="i usually meme.jpg" server="ftp.luisintiascaledmodels.com/public_html/" local="130631743847420201" remote="130630837200000000" Dst="0" />
<file name="imaga.JPG" server="ftp.luisintiascaledmodels.com/public_html/" local="130631744148427418" remote="130630977000000000" Dst="0" />
<file name="mario bros..PNG" server="ftp.luisintiascaledmodels.com/public_html/" local="130631744210840987" remote="130630960200000000" Dst="0" />
<file name="mle3.jpg" server="ftp.luisintiascaledmodels.com/public_html/" local="130631744270624407" remote="130627644000000000" Dst="0" />
<file name="imagae.JPG" server="ftp.luisintiascaledmodels.com/public_html/" local="130631744272634522" remote="130630972200000000" Dst="0" />
<file name="image2.JPG" server="ftp.luisintiascaledmodels.com/public_html/" local="130631744298566005" remote="130630972200000000" Dst="0" />
<file name="resort5.jpg" server="ftp.luisintiascaledmodels.com/public_html/" local="130631744305566405" remote="130627644000000000" Dst="0" />
<file name="rm3.jpg" server="ftp.luisintiascaledmodels.com/public_html/" local="130631744312706814" remote="130627644000000000" Dst="0" />
<file name="summer.jpg" server="ftp.luisintiascaledmodels.com/public_html/" local="130631744330957858" remote="130627644000000000" Dst="0" />
<file name="vm1.jpg" server="ftp.luisintiascaledmodels.com/public_html/" local="130631744331217873" remote="130630307400000000" Dst="0" />
<file name="vm2.jpg" server="ftp.luisintiascaledmodels.com/public_html/" local="130631744341138440" remote="130630307400000000" Dst="0" />
<file name="vm4.jpg" server="ftp.luisintiascaledmodels.com/public_html/" local="130631744363979746" remote="130630307400000000" Dst="0" />
<file name="vm3.jpg" server="ftp.luisintiascaledmodels.com/public_html/" local="130631744370930144" remote="130630307400000000" Dst="0" />
<file name="vm5.jpg" server="ftp.luisintiascaledmodels.com/public_html/" local="130631744370930144" remote="130630307400000000" Dst="0" />
<file name="vm6.jpg" server="ftp.luisintiascaledmodels.com/public_html/" local="130631744388541151" remote="130630307400000000" Dst="0" />
<file name="cmaa6.jpg" server="ftp.byethost24.com//htdocs/" local="130631743772325906" remote="130631284800000000" Dst="0" />
<file name="i usually meme.jpg" server="ftp.byethost24.com//htdocs/" local="130631743847420201" remote="130631284800000000" Dst="0" />
<file name="imaga.JPG" server="ftp.byethost24.com//htdocs/" local="130631744148427418" remote="130631285400000000" Dst="0" />
</dwsync>